[
    {
        "name" : "Attributes.Primary.Strength",
        "1" : 11,
        "2": 12,
        "3": 13,
        "5": 15,
        "8": 18,
        "13": 23,
        "21": 31,
        "34": 44,
        "55": 65
    },
    {
        "name" : "Attributes.Primary.Dexterity",
        "1" : 13,
        "2": 16,
        "3": 19,
        "5": 25,
        "8": 34,
        "13": 49,
        "21": 73,
        "34": 112,
        "55": 175
    },
    {
        "name" : "Attributes.Primary.Intelligence",
        "1" : 15,
        "2": 20,
        "3": 25,
        "5": 35,
        "8": 50,
        "13": 75,
        "21": 115,
        "34": 180,
        "55": 285
    },
    {
        "name" : "Attributes.Primary.Vigor",
        "1" : 22,
        "2": 24,
        "3": 26,
        "5": 30,
        "8": 36,
        "13": 46,
        "21": 62,
        "34": 88,
        "55": 130
    },
    {
        "name" : "Attributes.Primary.Spirit",
        "1" : 20,
        "2": 25,
        "3": 30,
        "5": 40,
        "8": 55,
        "13": 80,
        "21": 120,
        "34": 185,
        "55": 290
    }
]